{"Tables": [{"PutRequest": {"Item": {"occupied": {"BOOL": false}, "libID": {"S": "carpenter"}, "reservable": {"BOOL": false}, "tabID": {"S": "CH20"}}}}, {"PutRequest": {"Item": {"occupied": {"BOOL": false}, "libID": {"S": "carpenter"}, "reservable": {"BOOL": false}, "tabID": {"S": "CH21"}}}}, {"PutRequest": {"Item": {"occupied": {"BOOL": false}, "libID": {"S": "carpenter"}, "reservable": {"BOOL": false}, "tabID": {"S": "CH22"}}}}, {"PutRequest": {"Item": {"occupied": {"BOOL": false}, "libID": {"S": "carpenter"}, "reservable": {"BOOL": false}, "tabID": {"S": "CH23"}}}}, {"PutRequest": {"Item": {"occupied": {"BOOL": false}, "libID": {"S": "carpenter"}, "reservable": {"BOOL": false}, "tabID": {"S": "CH24"}}}}, {"PutRequest": {"Item": {"occupied": {"BOOL": false}, "libID": {"S": "carpenter"}, "reservable": {"BOOL": false}, "tabID": {"S": "CH25"}}}}, {"PutRequest": {"Item": {"occupied": {"BOOL": false}, "libID": {"S": "carpenter"}, "reservable": {"BOOL": false}, "tabID": {"S": "CH26"}}}}, {"PutRequest": {"Item": {"occupied": {"BOOL": false}, "libID": {"S": "carpenter"}, "reservable": {"BOOL": false}, "tabID": {"S": "CH27"}}}}, {"PutRequest": {"Item": {"occupied": {"BOOL": false}, "libID": {"S": "carpenter"}, "reservable": {"BOOL": false}, "tabID": {"S": "CH28"}}}}, {"PutRequest": {"Item": {"occupied": {"BOOL": false}, "libID": {"S": "carpenter"}, "reservable": {"BOOL": false}, "tabID": {"S": "CH29"}}}}, {"PutRequest": {"Item": {"occupied": {"BOOL": false}, "libID": {"S": "carpenter"}, "reservable": {"BOOL": false}, "tabID": {"S": "CH30"}}}}, {"PutRequest": {"Item": {"occupied": {"BOOL": false}, "libID": {"S": "carpenter"}, "reservable": {"BOOL": false}, "tabID": {"S": "CH31"}}}}, {"PutRequest": {"Item": {"occupied": {"BOOL": false}, "libID": {"S": "carpenter"}, "reservable": {"BOOL": false}, "tabID": {"S": "CH32"}}}}, {"PutRequest": {"Item": {"occupied": {"BOOL": false}, "libID": {"S": "carpenter"}, "reservable": {"BOOL": false}, "tabID": {"S": "CH33"}}}}, {"PutRequest": {"Item": {"occupied": {"BOOL": false}, "libID": {"S": "carpenter"}, "reservable": {"BOOL": false}, "tabID": {"S": "CH34"}}}}, {"PutRequest": {"Item": {"occupied": {"BOOL": false}, "libID": {"S": "carpenter"}, "reservable": {"BOOL": false}, "tabID": {"S": "CH35"}}}}, {"PutRequest": {"Item": {"occupied": {"BOOL": false}, "libID": {"S": "carpenter"}, "reservable": {"BOOL": false}, "tabID": {"S": "CH36"}}}}, {"PutRequest": {"Item": {"occupied": {"BOOL": false}, "libID": {"S": "carpenter"}, "reservable": {"BOOL": false}, "tabID": {"S": "CH37"}}}}, {"PutRequest": {"Item": {"occupied": {"BOOL": false}, "libID": {"S": "carpenter"}, "reservable": {"BOOL": false}, "tabID": {"S": "CH38"}}}}, {"PutRequest": {"Item": {"occupied": {"BOOL": false}, "libID": {"S": "carpenter"}, "reservable": {"BOOL": false}, "tabID": {"S": "CH39"}}}}]}