{"Tables": [{"PutRequest": {"Item": {"occupied": {"BOOL": false}, "libID": {"S": "uris"}, "reservable": {"BOOL": false}, "tabID": {"S": "UL124"}}}}, {"PutRequest": {"Item": {"occupied": {"BOOL": false}, "libID": {"S": "gates"}, "reservable": {"BOOL": false}, "tabID": {"S": "GATES0"}}}}, {"PutRequest": {"Item": {"occupied": {"BOOL": false}, "libID": {"S": "gates"}, "reservable": {"BOOL": false}, "tabID": {"S": "GATES1"}}}}, {"PutRequest": {"Item": {"occupied": {"BOOL": false}, "libID": {"S": "gates"}, "reservable": {"BOOL": false}, "tabID": {"S": "GATES2"}}}}, {"PutRequest": {"Item": {"occupied": {"BOOL": false}, "libID": {"S": "gates"}, "reservable": {"BOOL": false}, "tabID": {"S": "GATES3"}}}}, {"PutRequest": {"Item": {"occupied": {"BOOL": false}, "libID": {"S": "gates"}, "reservable": {"BOOL": false}, "tabID": {"S": "GATES4"}}}}, {"PutRequest": {"Item": {"occupied": {"BOOL": false}, "libID": {"S": "gates"}, "reservable": {"BOOL": false}, "tabID": {"S": "GATES5"}}}}, {"PutRequest": {"Item": {"occupied": {"BOOL": false}, "libID": {"S": "gates"}, "reservable": {"BOOL": false}, "tabID": {"S": "GATES6"}}}}, {"PutRequest": {"Item": {"occupied": {"BOOL": false}, "libID": {"S": "gates"}, "reservable": {"BOOL": false}, "tabID": {"S": "GATES7"}}}}, {"PutRequest": {"Item": {"occupied": {"BOOL": false}, "libID": {"S": "gates"}, "reservable": {"BOOL": false}, "tabID": {"S": "GATES8"}}}}, {"PutRequest": {"Item": {"occupied": {"BOOL": false}, "libID": {"S": "gates"}, "reservable": {"BOOL": false}, "tabID": {"S": "GATES9"}}}}, {"PutRequest": {"Item": {"occupied": {"BOOL": false}, "libID": {"S": "gates"}, "reservable": {"BOOL": false}, "tabID": {"S": "GATES10"}}}}, {"PutRequest": {"Item": {"occupied": {"BOOL": false}, "libID": {"S": "gates"}, "reservable": {"BOOL": false}, "tabID": {"S": "GATES11"}}}}, {"PutRequest": {"Item": {"occupied": {"BOOL": false}, "libID": {"S": "gates"}, "reservable": {"BOOL": false}, "tabID": {"S": "GATES12"}}}}, {"PutRequest": {"Item": {"occupied": {"BOOL": false}, "libID": {"S": "gates"}, "reservable": {"BOOL": false}, "tabID": {"S": "GATES13"}}}}, {"PutRequest": {"Item": {"occupied": {"BOOL": false}, "libID": {"S": "gates"}, "reservable": {"BOOL": false}, "tabID": {"S": "GATES14"}}}}, {"PutRequest": {"Item": {"occupied": {"BOOL": false}, "libID": {"S": "gates"}, "reservable": {"BOOL": false}, "tabID": {"S": "GATES15"}}}}, {"PutRequest": {"Item": {"occupied": {"BOOL": false}, "libID": {"S": "gates"}, "reservable": {"BOOL": false}, "tabID": {"S": "GATES16"}}}}, {"PutRequest": {"Item": {"occupied": {"BOOL": false}, "libID": {"S": "gates"}, "reservable": {"BOOL": false}, "tabID": {"S": "GATES17"}}}}, {"PutRequest": {"Item": {"occupied": {"BOOL": false}, "libID": {"S": "gates"}, "reservable": {"BOOL": false}, "tabID": {"S": "GATES18"}}}}]}